irflowservice/__init__.py
irflowservice/__main__.py
irflowservice/_version.py
irflowservice/app.py
irflowservice/requesthandlers.py
irflowservice/_config/__init__.py
irflowservice/_config/app/__init__.py
irflowservice/_config/app/dxlclient.config
irflowservice/_config/app/irflowservice.config
irflowservice/_config/app/logging.config
irflowservice/_config/sample/__init__.py
irflowservice/_config/sample/dxlclient.config
irflowservice-0.1.0.dist-info/LICENSE
irflowservice-0.1.0.dist-info/METADATA
irflowservice-0.1.0.dist-info/WHEEL
irflowservice-0.1.0.dist-info/top_level.txt
irflowservice-0.1.0.dist-info/RECORD
